playwright_network_spy/__init__.py
playwright_network_spy/py.typed
playwright_network_spy/spy.py
playwright_network_spy-0.1.4.dist-info/LICENSE
playwright_network_spy-0.1.4.dist-info/METADATA
playwright_network_spy-0.1.4.dist-info/WHEEL
playwright_network_spy-0.1.4.dist-info/RECORD
