Metadata-Version: 2.1
Name: playwright-network-spy
Version: 0.1.4
Summary: 🔥 A powerful tool for crawling any website on Earth with infinite scrolling, using Playwright.
Home-page: https://github.com/code-yeongyu/playwright-page-pool
License: MIT
Author: YeonGyu-Kim
Author-email: code.yeon.gyu@gmail.com
Requires-Python: >=3.8,<4.0
Classifier: License :: OSI Approved :: MIT License
Classifier: Programming Language :: Python :: 3
Classifier: Programming Language :: Python :: 3.8
Classifier: Programming Language :: Python :: 3.9
Classifier: Programming Language :: Python :: 3.10
Classifier: Programming Language :: Python :: 3.11
Classifier: Programming Language :: Python :: 3.12
Requires-Dist: pip
Requires-Dist: playwright
Project-URL: Repository, https://github.com/code-yeongyu/playwright-page-pool
